{
    "1800": "There is Human Capital",
    "2098": "There is Human Capital",
    "2178": "There is Human Capital",
    "2488": "There is Human Capital",
    "3197": "There is Human Capital",
    "3453": "There is Human Capital",
    "3570": "There is Human Capital",
    "4281": "There is Human Capital",
    "4447": "There is Human Capital",
    "4904": "There is Human Capital",
    "4977": "There is Human Capital",
    "5272": "There is Human Capital",
    "5513": "There is Human Capital",
    "5981": "There is Human Capital",
    "6176": "There is Human Capital",
    "7039": "There is Human Capital",
    "7084": "There is Human Capital",
    "7332": "There is Human Capital",
    "7431": "There is Human Capital",
    "7536": "There is Human Capital",
    "7789": "There is Human Capital",
    "8063": "There is Human Capital",
    "8818": "There is Human Capital",
    "9092": "There is Human Capital",
    "9326": "There is Human Capital",
    "9346": "There is Human Capital",
    "9389": "There is Human Capital",
    "9984": "There is Human Capital",
    "10456": "There is Human Capital",
    "11544": "There is Human Capital",
    "12208": "There is Human Capital",
    "12927": "There is Human Capital",
    "14272": "There is Human Capital",
    "14930": "There is Human Capital",
    "15615": "There is Human Capital",
    "18230": "There is Human Capital",
    "18349": "There is Human Capital",
    "18926": "There is Human Capital",
    "19411": "There is Human Capital",
    "19584": "There is Human Capital",
    "19612": "There is Human Capital",
    "19617": "There is Human Capital",
    "19745": "There is Human Capital",
    "20212": "There is Human Capital",
    "20520": "There is Human Capital",
    "21175": "There is Human Capital",
    "21344": "There is Human Capital",
    "21535": "There is Human Capital",
    "21665": "There is Human Capital",
    "22356": "There is Human Capital",
    "22701": "There is Human Capital",
    "23111": "There is Human Capital",
    "23194": "There is Human Capital",
    "24090": "There is Human Capital",
    "24491": "There is Human Capital",
    "24545": "There is Human Capital",
    "24741": "There is Human Capital",
    "25232": "There is Human Capital",
    "25445": "There is Human Capital",
    "25475": "There is Human Capital",
    "25743": "There is Human Capital",
    "26058": "There is Human Capital",
    "26172": "There is Human Capital",
    "26324": "There is Human Capital",
    "26780": "There is Human Capital",
    "27904": "There is Human Capital",
    "27996": "There is Human Capital",
    "28412": "There is Human Capital",
    "28823": "There is Human Capital",
    "29002": "There is Human Capital",
    "29669": "There is Human Capital",
    "29905": "There is Human Capital",
    "29989": "There is Human Capital",
    "30305": "There is Human Capital",
    "30625": "There is Human Capital",
    "30697": "There is Human Capital",
    "31107": "There is Human Capital",
    "31462": "There is Human Capital",
    "31791": "There is Human Capital",
    "33213": "There is Human Capital",
    "34067": "There is Human Capital",
    "34903": "There is Human Capital",
    "35214": "There is Human Capital",
    "35527": "There is Human Capital",
    "36029": "There is Human Capital",
    "36047": "There is Human Capital",
    "36270": "There is Human Capital",
    "36377": "There is Human Capital",
    "36506": "There is Human Capital",
    "37785": "There is Human Capital",
    "37808": "There is Human Capital",
    "37996": "There is Human Capital",
    "38725": "There is Human Capital",
    "39263": "There is Human Capital",
    "39899": "There is Human Capital",
    "40211": "There is Human Capital",
    "40533": "There is Human Capital",
    "40729": "There is Human Capital",
    "40888": "There is Human Capital",
    "40987": "There is Human Capital",
    "42682": "There is Human Capital",
    "42888": "There is Human Capital",
    "43196": "There is Human Capital",
    "45876": "There is Human Capital",
    "46080": "There is Human Capital",
    "46129": "There is Human Capital",
    "46195": "There is Human Capital",
    "47111": "There is Human Capital",
    "48039": "There is Human Capital",
    "48287": "There is Human Capital",
    "48898": "There is Human Capital",
    "49071": "There is Human Capital",
    "49196": "There is Human Capital",
    "49754": "There is Human Capital",
    "49826": "There is Human Capital",
    "50863": "There is Human Capital",
    "51143": "There is Human Capital",
    "51434": "There is Human Capital",
    "52827": "There is Human Capital",
    "54381": "There is Human Capital",
    "54480": "There is Human Capital",
    "55067": "There is Human Capital",
    "55135": "There is Human Capital",
    "56047": "There is Human Capital",
    "58492": "There is Human Capital",
    "59255": "There is Human Capital",
    "59440": "There is Human Capital",
    "59478": "There is Human Capital",
    "59527": "There is Human Capital",
    "59558": "There is Human Capital",
    "60086": "There is Human Capital",
    "60714": "There is Human Capital",
    "60977": "There is Human Capital",
    "61398": "There is Human Capital",
    "61986": "There is Human Capital",
    "62234": "There is Human Capital",
    "62709": "There is Human Capital",
    "62996": "There is Human Capital",
    "63276": "There is Human Capital",
    "63908": "There is Human Capital",
    "64040": "There is Human Capital",
    "64803": "There is Human Capital",
    "64996": "There is Human Capital",
    "65596": "There is Human Capital",
    "65984": "There is Human Capital",
    "66570": "There is Human Capital",
    "66740": "There is Human Capital",
    "66756": "There is Human Capital",
    "67716": "There is Human Capital",
    "68505": "There is Human Capital",
    "69488": "There is Human Capital",
    "70318": "There is Human Capital",
    "70415": "There is Human Capital",
    "70487": "There is Human Capital",
    "70858": "There is Human Capital",
    "71691": "There is Human Capital",
    "72162": "There is Human Capital",
    "72741": "There is Human Capital",
    "72903": "There is Human Capital",
    "72971": "There is Human Capital",
    "73088": "There is Human Capital",
    "73124": "There is Human Capital",
    "73309": "There is Human Capital",
    "73756": "There is Human Capital",
    "74208": "There is Human Capital",
    "74303": "There is Human Capital",
    "75208": "There is Human Capital",
    "75252": "There is Human Capital",
    "75362": "There is Human Capital",
    "75677": "There is Human Capital",
    "76282": "There is Human Capital",
    "76605": "There is Human Capital",
    "77281": "There is Human Capital",
    "77360": "There is Human Capital",
    "77476": "There is Human Capital",
    "77543": "There is Human Capital",
    "77877": "There is Human Capital",
    "78003": "There is Human Capital",
    "78128": "There is Human Capital",
    "78814": "There is Human Capital",
    "78890": "There is Human Capital",
    "79282": "There is Human Capital",
    "80035": "There is Human Capital",
    "80172": "There is Human Capital",
    "80661": "There is Human Capital",
    "82811": "There is Human Capital",
    "84246": "There is Human Capital",
    "84748": "There is Human Capital",
    "85961": "There is Human Capital",
    "86312": "There is Human Capital",
    "87347": "There is Human Capital",
    "88121": "There is Human Capital",
    "88205": "There is Human Capital",
    "89439": "There is Human Capital",
    "89800": "There is Human Capital",
    "90498": "There is Human Capital",
    "91142": "There is Human Capital",
    "91440": "There is Human Capital",
    "91576": "There is Human Capital",
    "91767": "There is Human Capital",
    "91928": "There is Human Capital",
    "92122": "There is Human Capital",
    "92230": "There is Human Capital",
    "92380": "There is Human Capital",
    "93389": "There is Human Capital",
    "93410": "There is Human Capital",
    "93556": "There is Human Capital",
    "94049": "There is Human Capital",
    "94344": "There is Human Capital",
    "95574": "There is Human Capital",
    "95953": "There is Human Capital",
    "96943": "There is Human Capital",
    "97134": "There is Human Capital",
    "97210": "There is Human Capital",
    "97216": "There is Human Capital",
    "97476": "There is Human Capital",
    "97745": "There is Human Capital",
    "98222": "There is Human Capital",
    "98362": "There is Human Capital",
    "99780": "There is Human Capital",
    "100517": "There is Human Capital",
    "100885": "There is Human Capital",
    "101199": "There is Human Capital",
    "101382": "There is Human Capital",
    "101778": "There is Human Capital",
    "101984": "There is Human Capital",
    "102212": "There is Human Capital",
    "102729": "There is Human Capital",
    "102752": "There is Human Capital",
    "103145": "There is Human Capital",
    "103730": "There is Human Capital",
    "104889": "There is Human Capital",
    "104894": "There is Human Capital",
    "105016": "There is Human Capital",
    "105319": "There is Human Capital",
    "105418": "There is Human Capital",
    "105634": "There is Human Capital",
    "105770": "There is Human Capital",
    "106535": "There is Human Capital",
    "106640": "There is Human Capital",
    "107263": "There is Human Capital",
    "109380": "There is Human Capital",
    "200406": "There is Human Capital",
    "203596": "There is Human Capital",
    "215466": "There is Human Capital",
    "216085": "There is Human Capital",
    "216228": "There is Human Capital",
    "217346": "There is Human Capital",
    "225648": "There is Human Capital",
    "230557": "There is Human Capital",
    "277135": "There is Human Capital",
    "277509": "There is Human Capital",
    "277948": "There is Human Capital",
    "310142": "There is Human Capital",
    "310158": "There is Human Capital",
    "310522": "There is Human Capital",
    "311094": "There is Human Capital",
    "313616": "There is Human Capital",
    "313927": "There is Human Capital",
    "314203": "There is Human Capital",
    "314489": "There is Human Capital",
    "315709": "There is Human Capital",
    "315852": "There is Human Capital",
    "316709": "There is Human Capital",
    "317540": "There is Human Capital",
    "318154": "There is Human Capital",
    "318300": "There is Human Capital",
    "318833": "There is Human Capital",
    "320335": "There is Human Capital",
    "350698": "There is Human Capital",
    "350852": "There is Human Capital",
    "350894": "There is Human Capital",
    "351569": "There is Human Capital",
    "351834": "There is Human Capital",
    "352541": "There is Human Capital",
    "352825": "There is Human Capital",
    "352915": "There is Human Capital",
    "353020": "There is Human Capital",
    "353569": "There is Human Capital",
    "354190": "There is Human Capital",
    "354707": "There is Human Capital",
    "354908": "There is Human Capital",
    "354963": "There is Human Capital",
    "355811": "There is Human Capital",
    "356171": "There is Human Capital",
    "357173": "There is Human Capital",
    "357301": "There is Human Capital",
    "700564": "There is Human Capital",
    "700565": "There is Human Capital",
    "700923": "There is Human Capital",
    "701288": "There is Human Capital",
    "701347": "There is Human Capital",
    "701374": "There is Human Capital",
    "702165": "There is Human Capital",
    "702513": "There is Human Capital",
    "703604": "There is Human Capital",
    "704415": "There is Human Capital",
    "704440": "There is Human Capital",
    "704532": "There is Human Capital",
    "706129": "There is Human Capital",
    "707179": "There is Human Capital",
    "708781": "There is Human Capital",
    "708821": "There is Human Capital",
    "708955": "There is Human Capital",
    "709005": "There is Human Capital",
    "709337": "There is Human Capital",
    "711669": "There is Human Capital",
    "711772": "There is Human Capital",
    "712034": "There is Human Capital",
    "712534": "There is Human Capital",
    "712537": "There is Human Capital",
    "713676": "There is Human Capital",
    "714310": "There is Human Capital",
    "714395": "There is Human Capital",
    "715072": "There is Human Capital",
    "715787": "There is Human Capital",
    "715957": "There is Human Capital",
    "716006": "There is Human Capital",
    "716634": "There is Human Capital",
    "717423": "There is Human Capital",
    "717538": "There is Human Capital",
    "717605": "There is Human Capital",
    "717806": "There is Human Capital",
    "718877": "There is Human Capital",
    "718937": "There is Human Capital",
    "719220": "There is Human Capital",
    "719413": "There is Human Capital"
}